[
    {
        "article-type": "editorial",
        "author": null,
        "date": "2024-02-04",
        "publication": "el-colombiano",
        "title": "Las buenas preguntas",
        "url": "https://www.elcolombiano.com/opinion/columnistas/las-buenas-preguntas-DB23665754"
    },
    {
        "article-type": "editorial",
        "author": null,
        "date": "2024-02-04",
        "publication": "el-espectador",
        "title": "En una democracia las reglas del juego se cumplen ",
        "url": "https://www.elespectador.com/opinion/editorial/en-una-democracia-las-reglas-del-juego-se-cumplen/"
    },
    {
        "article-type": "column",
        "author": "Fernando Ara\u00fajo V\u00e9lez",
        "date": "2024-02-04",
        "publication": "el-espectador",
        "title": " Yo te defino, t\u00fa me defines",
        "url": "https://www.elespectador.com/opinion/columnistas/fernando-araujo-velez/yo-te-defino-tu-me-defines-el-caminante/"
    },
    {
        "article-type": "column",
        "author": "Ramiro Bejarano Guzm\u00e1n",
        "date": "2024-02-04",
        "publication": "el-espectador",
        "title": "Oposici\u00f3n vs. difamaci\u00f3n",
        "url": "https://www.elespectador.com/opinion/columnistas/ramiro-bejarano-guzman/oposicion-vs-difamacion/"
    },
    {
        "article-type": "column",
        "author": "Laura Ardila Arrieta",
        "date": "2024-02-04",
        "publication": "el-espectador",
        "title": "Reyezuelos en Sincelejo ",
        "url": "https://www.elespectador.com/opinion/columnistas/laura-ardila-arrieta/reyezuelos-en-sincelejo/"
    },
    {
        "article-type": "column",
        "author": "Rodrigo Uprimny",
        "date": "2024-02-04",
        "publication": "el-espectador",
        "title": "Corte Suprema y elecci\u00f3n de fiscal",
        "url": "https://www.elespectador.com/opinion/columnistas/rodrigo-uprimny/corte-suprema-y-eleccion-de-fiscal/"
    },
    {
        "article-type": "column",
        "author": "Piedad Bonnett",
        "date": "2024-02-04",
        "publication": "el-espectador",
        "title": "\u201cEl m\u00e1s lento en prometer...\u201d",
        "url": "https://www.elespectador.com/opinion/columnistas/piedad-bonnett/el-mas-lento-en-prometer-2/"
    },
    {
        "article-type": "column",
        "author": "H\u00e9ctor Abad Faciolince",
        "date": "2024-02-04",
        "publication": "el-espectador",
        "title": "Amigos m\u00edos",
        "url": "https://www.elespectador.com/opinion/columnistas/hector-abad-faciolince/amigos-mios/"
    },
    {
        "article-type": "column",
        "author": "Tola y Maruja",
        "date": "2024-02-04",
        "publication": "el-espectador",
        "title": "Tola y Maruja buscan la eutanasia",
        "url": "https://www.elespectador.com/opinion/columnistas/tola-y-maruja/tola-y-maruja-buscan-la-eutanasia/"
    },
    {
        "article-type": "column",
        "author": "Irene Vallejo Moreu",
        "date": "2024-02-04",
        "publication": "el-espectador",
        "title": "La carne de la memoria",
        "url": "https://www.elespectador.com/opinion/columnistas/ivallejo/la-carne-de-la-memoria/"
    },
    {
        "article-type": "column",
        "author": "Armando Montenegro",
        "date": "2024-02-04",
        "publication": "el-espectador",
        "title": "El ocaso de la descentralizaci\u00f3n",
        "url": "https://www.elespectador.com/opinion/columnistas/armando-montenegro/el-ocaso-de-la-descentralizacion/"
    },
    {
        "article-type": "column",
        "author": "Mauricio Botero Caicedo",
        "date": "2024-02-04",
        "publication": "el-espectador",
        "title": "Sin guarida asegurada, no dejar\u00e1n el poder",
        "url": "https://www.elespectador.com/opinion/columnistas/mauricio-botero-caicedo/sin-guarida-asegurada-no-dejaran-el-poder/"
    },
    {
        "article-type": "column",
        "author": "Jaime Bayly",
        "date": "2024-02-04",
        "publication": "el-espectador",
        "title": "El impuntual",
        "url": "https://www.elespectador.com/opinion/columnistas/jbayly/el-impuntual/"
    },
    {
        "article-type": "column",
        "author": "William Ospina",
        "date": "2024-02-04",
        "publication": "el-espectador",
        "title": "C\u00e1mbialo todo, pero no toques nada",
        "url": "https://www.elespectador.com/opinion/columnistas/william-ospina/cambialo-todo-pero-no-toques-nada/"
    },
    {
        "article-type": "column",
        "author": "Tatiana Acevedo Guerrero",
        "date": "2024-02-04",
        "publication": "el-espectador",
        "title": "Tollos, rayas y quimeras I",
        "url": "https://www.elespectador.com/opinion/columnistas/tatiana-acevedo-guerrero/tollos-rayas-y-quimeras-i/"
    },
    {
        "article-type": "column",
        "author": "Felipe Zuleta Lleras",
        "date": "2024-02-04",
        "publication": "el-espectador",
        "title": "El inepto",
        "url": "https://www.elespectador.com/opinion/columnistas/felipe-zuleta-lleras/el-inepto/"
    },
    {
        "article-type": "column",
        "author": "Carlos Enrique Moreno",
        "date": "2024-02-04",
        "publication": "el-espectador",
        "title": "Reformas y control pol\u00edtico del ciudadano",
        "url": "https://www.elespectador.com/opinion/columnistas/carlos-enrique-moreno/reformas-y-control-politico-del-ciudadano/"
    },
    {
        "article-type": "column",
        "author": "Piedad Bonnett",
        "date": "2024-02-04",
        "publication": "el-espectador",
        "title": "\u201cEl m\u00e1s lento en prometer\u2026\u201d",
        "url": "https://www.elespectador.com/opinion/columnistas/piedad-bonnett/el-mas-lento-en-prometer/"
    },
    {
        "article-type": "editorial",
        "author": null,
        "date": "2024-02-04",
        "publication": "el-tiempo",
        "title": "Rodear a la Corte Suprema",
        "url": "https://www.eltiempo.com/opinion/editorial/editorial-de-el-tiempo-del-4-de-febrero-de-2024-rodear-a-la-corte-suprema-851369"
    },
    {
        "article-type": "column",
        "author": "Germ\u00e1n Vargas Lleras",
        "date": "2024-02-04",
        "publication": "el-tiempo",
        "title": "Las \u2018petrogiras\u2019",
        "url": "https://www.eltiempo.com/opinion/columnistas/german-vargas-lleras/columna-de-german-vargas-lleras-las-petrogiras-851372"
    },
    {
        "article-type": "column",
        "author": "Mar\u00eda Isabel Rueda",
        "date": "2024-02-04",
        "publication": "el-tiempo",
        "title": "El golpe blando de Petro",
        "url": "https://www.eltiempo.com/opinion/columnistas/maria-isabel-rueda/columna-de-maria-isabel-rueda-el-golpe-blando-de-petro-851388"
    },
    {
        "article-type": "column",
        "author": "N\u00e9stor Humberto Mart\u00ednez",
        "date": "2024-02-04",
        "publication": "el-tiempo",
        "title": "El d\u00e9ficit y los \u00e1rbitros chepitos",
        "url": "https://www.eltiempo.com/opinion/columnistas/nestor-humberto-martinez/columna-de-nestor-humberto-martinez-el-deficit-y-los-arbitros-chepitos-851401"
    },
    {
        "article-type": "column",
        "author": "Mauricio Vargas",
        "date": "2024-02-04",
        "publication": "el-tiempo",
        "title": "El silencio de los culpables",
        "url": "https://www.eltiempo.com/opinion/columnistas/mauricio-vargas/columna-de-mauricio-vargas-el-silencio-de-los-culpables-851370"
    },
    {
        "article-type": "column",
        "author": "C\u00e9sar Ferrari",
        "date": "2024-02-04",
        "publication": "el-tiempo",
        "title": "Medios de pago, inflaci\u00f3n o crecimiento",
        "url": "https://www.eltiempo.com/opinion/columnistas/otros-columnistas/columna-de-cesar-ferrari-medios-de-pago-inflacion-o-crecimiento-851403"
    },
    {
        "article-type": "column",
        "author": "Thierry Ways",
        "date": "2024-02-04",
        "publication": "el-tiempo",
        "title": "El gabinete en llamas",
        "url": "https://www.eltiempo.com/opinion/columnistas/thierry-ways/columna-de-thierry-ways-el-gabinete-en-llamas-851389"
    },
    {
        "article-type": "column",
        "author": "Sergio Clavijo",
        "date": "2024-02-04",
        "publication": "el-tiempo",
        "title": "Empresas, inflaci\u00f3n y crecimiento",
        "url": "https://www.eltiempo.com/opinion/columnistas/sergio-clavijo/empresas-inflacion-y-crecimiento-851390"
    },
    {
        "article-type": "column",
        "author": "Juan Pablo Salazar",
        "date": "2024-02-04",
        "publication": "el-tiempo",
        "title": "Una oportunidad de inclusi\u00f3n que se pierde",
        "url": "https://www.eltiempo.com/opinion/columnistas/juan-pablo-salazar/columna-de-juan-pablo-salazar-una-oportunidad-de-inclusion-que-se-pierde-851402"
    }
]
