[
    {
        "article-type": "editorial",
        "author": null,
        "date": "2023-04-01",
        "publication": "el-colombiano",
        "title": "",
        "url": "https://www.elcolombiano.com/opinion/editoriales/dios-y-el-diablo-en-el-estado-KD20987940"
    },
    {
        "article-type": "column",
        "author": "Diego Mesa Puyo",
        "date": "2023-04-01",
        "publication": "el-colombiano",
        "title": "Felicidad con F de Finlandia",
        "url": "https://www.elcolombiano.com/opinion/columnistas/felicidad-con-f-de-finlandia-OD20987328"
    },
    {
        "article-type": "column",
        "author": "Ernesto Ochoa Moreno",
        "date": "2023-04-01",
        "publication": "el-colombiano",
        "title": "Semana Santa: una meditaci\u00f3n, por si acaso",
        "url": "https://www.elcolombiano.com/opinion/columnistas/semana-santa-una-meditacion-por-si-acaso-CD20987306"
    },
    {
        "article-type": "column",
        "author": "Jos\u00e9 Guillermo \u00c1ngel",
        "date": "2023-04-01",
        "publication": "el-colombiano",
        "title": "Sobre hacer y pensar menos",
        "url": "https://www.elcolombiano.com/opinion/columnistas/sobre-hacer-y-pensar-menos-PD20987282"
    },
    {
        "article-type": "column",
        "author": "Adriana Correa Vel\u00e1squez",
        "date": "2023-04-01",
        "publication": "el-colombiano",
        "title": "Lo que la m\u00fasica le dice a la medicina ",
        "url": "https://www.elcolombiano.com/opinion/columnistas/lo-que-la-musica-le-dice-a-la-medicina-BD20987240"
    },
    {
        "article-type": "column",
        "author": "Juan Espinal",
        "date": "2023-04-01",
        "publication": "el-colombiano",
        "title": "",
        "url": "https://www.elcolombiano.com/opinion/columnistas/senor-fiscal-salve-usted-la-patria-JD20987178"
    },
    {
        "article-type": "column",
        "author": "Jos\u00e9 Manuel Restrepo Abondano",
        "date": "2023-03-31",
        "publication": "el-colombiano",
        "title": "Sabor agridulce de reforma pensional",
        "url": "https://www.elcolombiano.com/opinion/columnistas/sabor-agridulce-de-reforma-pensional-CN20967243"
    },
    {
        "article-type": "column",
        "author": "Diego Aristiz\u00e1bal",
        "date": "2023-03-31",
        "publication": "el-colombiano",
        "title": "Cierren esa biblioteca",
        "url": "https://www.elcolombiano.com/opinion/columnistas/cierren-esa-biblioteca-ON20966844"
    },
    {
        "article-type": "column",
        "author": "Luis Fernando \u00c1lvarez",
        "date": "2023-03-31",
        "publication": "el-colombiano",
        "title": "Democracia en riesgo: el caso colombiano",
        "url": "https://www.elcolombiano.com/opinion/columnistas/democracia-en-riesgo-el-caso-colombiano-EN20966736"
    },
    {
        "article-type": "column",
        "author": "Henry Medina Uribe",
        "date": "2023-03-31",
        "publication": "el-colombiano",
        "title": "El monopolio leg\u00edtimo de la fuerza ",
        "url": "https://www.elcolombiano.com/opinion/columnistas/el-monopolio-legitimo-de-la-fuerza-FN20966461"
    },
    {
        "article-type": "column",
        "author": "Invitado",
        "date": "2023-03-31",
        "publication": "el-colombiano",
        "title": "\u00a1Rejas No! Un gran acuerdo social para el espacio p\u00fablico de Medell\u00edn ",
        "url": "https://www.elcolombiano.com/opinion/columnistas/rejas-no-un-gran-acuerdo-social-para-el-espacio-publico-de-medellin-ON20966338"
    },
    {
        "article-type": "editorial",
        "author": null,
        "date": "2023-04-01",
        "publication": "el-espectador",
        "title": "Los muertos que parecen importar poco ",
        "url": "https://www.elespectador.com/opinion/editorial/los-muertos-que-parecen-importar-poco/"
    },
    {
        "article-type": "column",
        "author": "Julio C\u00e9sar Londo\u00f1o",
        "date": "2023-04-01",
        "publication": "el-espectador",
        "title": "La oraci\u00f3n del ateo",
        "url": "https://www.elespectador.com/opinion/columnistas/julio-cesar-londono/la-oracion-del-ateo-2/"
    },
    {
        "article-type": "column",
        "author": "Nicol\u00e1s Rodr\u00edguez",
        "date": "2023-04-01",
        "publication": "el-espectador",
        "title": "TikTok, la nueva bomba",
        "url": "https://www.elespectador.com/opinion/columnistas/nicolas-rodriguez/tiktok-la-nueva-bomba/"
    },
    {
        "article-type": "column",
        "author": "Santiago Gamboa",
        "date": "2023-04-01",
        "publication": "el-espectador",
        "title": "Huelgas",
        "url": "https://www.elespectador.com/opinion/columnistas/santiago-gamboa/huelgas/"
    },
    {
        "article-type": "column",
        "author": "Mauricio Garc\u00eda Villegas",
        "date": "2023-04-01",
        "publication": "el-espectador",
        "title": "El diablo y la Polic\u00eda",
        "url": "https://www.elespectador.com/opinion/columnistas/mauricio-garcia-villegas/el-diablo-y-la-policia/"
    },
    {
        "article-type": "column",
        "author": "Catalina Uribe Rinc\u00f3n",
        "date": "2023-04-01",
        "publication": "el-espectador",
        "title": "Trabajar m\u00e1s para ganar menos",
        "url": "https://www.elespectador.com/opinion/columnistas/catalina-uribe-rincon/trabajar-mas-para-ganar-menos/"
    },
    {
        "article-type": "column",
        "author": "Sorayda Peguero Isaac",
        "date": "2023-04-01",
        "publication": "el-espectador",
        "title": "\u00bfY t\u00fa, qu\u00e9 has hecho?",
        "url": "https://www.elespectador.com/opinion/columnistas/sorayda-peguero/y-tu-que-has-hecho/"
    },
    {
        "article-type": "column",
        "author": "Juan Manuel Ospina",
        "date": "2023-04-01",
        "publication": "el-espectador",
        "title": "La reforma pensional... \u00bfdar\u00e1 en el blanco?",
        "url": "https://www.elespectador.com/opinion/columnistas/juan-manuel-ospina/la-reforma-pensional-dara-en-el-blanco/"
    },
    {
        "article-type": "column",
        "author": "Alejandro \u00c1lvarez",
        "date": "2023-04-01",
        "publication": "el-espectador",
        "title": "M\u00e1s all\u00e1 de los aprendizajes b\u00e1sicos",
        "url": "https://www.elespectador.com/opinion/columnistas/alejandro-alvarez/mas-alla-de-los-aprendizajes-basicos/"
    },
    {
        "article-type": "column",
        "author": "Juan David Ochoa",
        "date": "2023-04-01",
        "publication": "el-espectador",
        "title": "El general reaccionario",
        "url": "https://www.elespectador.com/opinion/columnistas/juan-david-ochoa/el-general-reaccionario/"
    },
    {
        "article-type": "column",
        "author": "Carolina Botero Cabrera",
        "date": "2023-04-01",
        "publication": "el-espectador",
        "title": "Ciencia abierta con Petro: mucho til\u00edn, til\u00edn y nada de paletas",
        "url": "https://www.elespectador.com/opinion/columnistas/carolina-botero-cabrera/ciencia-abierta-con-petro-mucho-tilin-tilin-y-nada-de-paletas/"
    },
    {
        "article-type": "column",
        "author": "Gonzalo Mallarino Fl\u00f3rez",
        "date": "2023-04-01",
        "publication": "el-espectador",
        "title": "M\u00e1s muchachos asesinados",
        "url": "https://www.elespectador.com/opinion/columnistas/gonzalo-mallarino/mas-muchachos-asesinados/"
    },
    {
        "article-type": "column",
        "author": "Columnista invitada",
        "date": "2023-04-01",
        "publication": "el-espectador",
        "title": "Sociedad civil en la \u2018Paz total\u2019: S\u00ed, pero \u00bfC\u00f3mo?",
        "url": "https://www.elespectador.com/colombia-20/analistas/sociedad-civil-en-la-paz-total-si-pero-como/"
    },
    {
        "article-type": "column",
        "author": "Kenneth Burbano Villamar\u00edn",
        "date": "2023-04-01",
        "publication": "el-espectador",
        "title": "\u00bfFanatismo y vulneraciones o libertad de culto y religi\u00f3n?",
        "url": "https://www.elespectador.com/colombia-20/analistas/fanatismo-y-vulneraciones-o-libertad-de-culto-y-religion/"
    },
    {
        "article-type": "column",
        "author": "Santiago Villa",
        "date": "2023-03-31",
        "publication": "el-espectador",
        "title": "Polic\u00eda, Estado y religi\u00f3n ",
        "url": "https://www.elespectador.com/opinion/columnistas/santiago-villa/policia-estado-y-religion/"
    },
    {
        "article-type": "column",
        "author": "Mario Fernando Prado",
        "date": "2023-03-31",
        "publication": "el-espectador",
        "title": "\u00bfUna alcaldesa para Cali?",
        "url": "https://www.elespectador.com/opinion/columnistas/mario-fernando-prado/una-alcaldesa-para-cali/"
    },
    {
        "article-type": "column",
        "author": "Juan Carlos Botero",
        "date": "2023-03-31",
        "publication": "el-espectador",
        "title": "Abu Ghraib",
        "url": "https://www.elespectador.com/opinion/columnistas/juan-carlos-botero/abu-ghraib/"
    },
    {
        "article-type": "editorial",
        "author": null,
        "date": "2023-04-01",
        "publication": "el-tiempo",
        "title": "Una extra\u00f1a indagaci\u00f3n",
        "url": "https://www.eltiempo.com/opinion/editorial/una-extrana-indagacion-editorial-el-tiempo-755644"
    },
    {
        "article-type": "column",
        "author": "Mauricio C\u00e1rdenas Santamar\u00eda",
        "date": "2023-04-01",
        "publication": "el-tiempo",
        "title": "\u00bfModeraci\u00f3n o radicalizaci\u00f3n?",
        "url": "https://www.eltiempo.com/opinion/columnistas/mauricio-cardenas-santamaria/moderacion-o-radicalizacion-columna-de-mauricio-cardenas-755618"
    },
    {
        "article-type": "column",
        "author": "Sara Tufano",
        "date": "2023-04-01",
        "publication": "el-tiempo",
        "title": "Los nudos ciegos de la \u2018Paz total\u2019",
        "url": "https://www.eltiempo.com/opinion/columnistas/sara-tufano/los-nudos-ciegos-de-la-paz-total-columna-de-sara-tufano-755567"
    },
    {
        "article-type": "column",
        "author": "Luis No\u00e9 Ochoa",
        "date": "2023-04-01",
        "publication": "el-tiempo",
        "title": "Derrotar al diablo",
        "url": "https://www.eltiempo.com/opinion/columnistas/luis-noe-ochoa/derrotar-al-diablo-columna-de-luis-noe-ochoa-755595"
    },
    {
        "article-type": "column",
        "author": "Jos\u00e9 Gregorio Hern\u00e1ndez",
        "date": "2023-04-01",
        "publication": "el-tiempo",
        "title": "La intervenci\u00f3n estatal",
        "url": "https://www.eltiempo.com/opinion/columnistas/jose-gregorio-hernandez/la-intervencion-estatal-columna-de-jose-gregorio-hernandez-755544"
    },
    {
        "article-type": "column",
        "author": "\u00d3scar Dom\u00ednguez Giraldo",
        "date": "2023-04-01",
        "publication": "el-tiempo",
        "title": "Lentejo modelo 2023",
        "url": "https://www.eltiempo.com/opinion/columnistas/oscar-dominguez-giraldo/lentejo-modelo-2023-columna-de-oscar-dominguez-giraldo-755582"
    },
    {
        "article-type": "column",
        "author": "Javier Borda Diaz",
        "date": "2023-04-01",
        "publication": "el-tiempo",
        "title": "No critiquen a todo el periodismo por un tuit",
        "url": "https://www.eltiempo.com/opinion/columnistas/javier-borda-diaz/no-critiquen-a-todo-el-periodismo-por-un-tuit-columna-de-javier-borda-755586"
    },
    {
        "article-type": "column",
        "author": "Pedro Javier Rojas Guevara",
        "date": "2023-04-01",
        "publication": "el-tiempo",
        "title": "Plan militar Ayacucho: esperanza de libertad y orden",
        "url": "https://www.eltiempo.com/opinion/columnistas/pedro-javier-rojas-guevara/plan-militar-ayacucho-esperanza-de-libertad-y-orden-pedro-javier-rojas-755585"
    }
]
