[
    {
        "article-type": "editorial",
        "author": null,
        "date": "2023-03-03",
        "publication": "el-colombiano",
        "title": "",
        "url": "https://www.elcolombiano.com/opinion/editoriales/la-dictadura-de-la-correccion-NA20648371"
    },
    {
        "article-type": "column",
        "author": "Alonso Salazar Jaramillo",
        "date": "2023-03-03",
        "publication": "el-colombiano",
        "title": "",
        "url": "https://www.elcolombiano.com/opinion/columnistas/ministros-despachados-por-la-puerta-de-atras-CA20648497"
    },
    {
        "article-type": "column",
        "author": "Henry Medina Uribe",
        "date": "2023-03-03",
        "publication": "el-colombiano",
        "title": "Hacia una paz precaria",
        "url": "https://www.elcolombiano.com/opinion/columnistas/hacia-una-paz-precaria-JA20647187"
    },
    {
        "article-type": "column",
        "author": "Jos\u00e9 Manuel Restrepo Abondano",
        "date": "2023-03-03",
        "publication": "el-colombiano",
        "title": "Inflaci\u00f3n de reformas, deflaci\u00f3n de confianza",
        "url": "https://www.elcolombiano.com/opinion/columnistas/inflacion-de-reformas-deflacion-de-confianza-LA20648535"
    },
    {
        "article-type": "column",
        "author": "Diego Aristiz\u00e1bal",
        "date": "2023-03-03",
        "publication": "el-colombiano",
        "title": "El lecho para las mil cosas",
        "url": "https://www.elcolombiano.com/opinion/columnistas/el-lecho-para-las-mil-cosas-EA20648408"
    },
    {
        "article-type": "column",
        "author": "Luis Fernando \u00c1lvarez",
        "date": "2023-03-03",
        "publication": "el-colombiano",
        "title": "Di\u00e1logo entre servidores sin competencia ",
        "url": "https://www.elcolombiano.com/opinion/columnistas/dialogo-entre-servidores-sin-competencia-LA20648311"
    },
    {
        "article-type": "column",
        "author": "Rodrigo Botero Montoya",
        "date": "2023-03-02",
        "publication": "el-colombiano",
        "title": "Sobre Pol\u00edtica Exterior",
        "url": "https://www.elcolombiano.com/opinion/columnistas/sobre-politica-exterior-AH20634631"
    },
    {
        "article-type": "column",
        "author": "Juan G\u00f3mez Mart\u00ednez",
        "date": "2023-03-02",
        "publication": "el-colombiano",
        "title": "Opinar con desconocimiento ",
        "url": "https://www.elcolombiano.com/opinion/columnistas/opinar-con-desconocimiento-AH20634756"
    },
    {
        "article-type": "column",
        "author": "Sara Jaramillo Klinkert",
        "date": "2023-03-02",
        "publication": "el-colombiano",
        "title": "Un minuto demasiado tarde ",
        "url": "https://www.elcolombiano.com/opinion/columnistas/un-minuto-demasiado-tarde-FH20634735"
    },
    {
        "article-type": "column",
        "author": "\u00d3scar Dom\u00ednguez Giraldo",
        "date": "2023-03-02",
        "publication": "el-colombiano",
        "title": "Manual para disculparse",
        "url": "https://www.elcolombiano.com/opinion/columnistas/manual-para-disculparse-CH20634677"
    },
    {
        "article-type": "column",
        "author": "Humberto Montero",
        "date": "2023-03-02",
        "publication": "el-colombiano",
        "title": "El ecocidio de Maduro",
        "url": "https://www.elcolombiano.com/opinion/columnistas/el-ecocidio-de-maduro-EH20634653"
    },
    {
        "article-type": "editorial",
        "author": null,
        "date": "2023-03-03",
        "publication": "el-espectador",
        "title": "Conflictos familiares",
        "url": "https://www.elespectador.com/opinion/editorial/conflictos-familiares/"
    },
    {
        "article-type": "column",
        "author": "Luis Fernando Montoya",
        "date": "2023-03-03",
        "publication": "el-espectador",
        "title": "Argentina, en la cima",
        "url": "https://www.elespectador.com/opinion/columnistas/luis-fernando-montoya/argentina-en-la-cima/"
    },
    {
        "article-type": "column",
        "author": "Arturo Guerrero",
        "date": "2023-03-03",
        "publication": "el-espectador",
        "title": "Los atroces pandilleros del atroz Bukele",
        "url": "https://www.elespectador.com/opinion/columnistas/arturo-guerrero/los-atroces-pandilleros-del-atroz-bukele/"
    },
    {
        "article-type": "column",
        "author": "Francisco Guti\u00e9rrez San\u00edn",
        "date": "2023-03-03",
        "publication": "el-espectador",
        "title": "Los ricos tambi\u00e9n lloran",
        "url": "https://www.elespectador.com/opinion/columnistas/francisco-gutierrez-sanin/los-ricos-tambien-lloran/"
    },
    {
        "article-type": "column",
        "author": "Mario Fernando Prado",
        "date": "2023-03-03",
        "publication": "el-espectador",
        "title": "Se vaci\u00f3 San Andr\u00e9s",
        "url": "https://www.elespectador.com/opinion/columnistas/mario-fernando-prado/se-vacio-san-andres/"
    },
    {
        "article-type": "column",
        "author": "Alfredo Molano Jimeno",
        "date": "2023-03-03",
        "publication": "el-espectador",
        "title": "Una mafia blindada en la UNP",
        "url": "https://www.elespectador.com/opinion/columnistas/alfredo-molano-jimeno/una-mafia-blindada-en-la-unp/"
    },
    {
        "article-type": "column",
        "author": "Juan Carlos Botero",
        "date": "2023-03-03",
        "publication": "el-espectador",
        "title": "Una visi\u00f3n equivocada",
        "url": "https://www.elespectador.com/opinion/columnistas/juan-carlos-botero/una-vision-equivocada/"
    },
    {
        "article-type": "column",
        "author": "Francisco Leal Buitrago",
        "date": "2023-03-03",
        "publication": "el-espectador",
        "title": "Propuestas de reformas (II)",
        "url": "https://www.elespectador.com/opinion/columnistas/francisco-leal-buitrago/propuestas-de-reformas-ii/"
    },
    {
        "article-type": "column",
        "author": "\u00d3scar Sevillano",
        "date": "2023-03-03",
        "publication": "el-espectador",
        "title": "Francia M\u00e1rquez, Dapa y el helic\u00f3ptero",
        "url": "https://www.elespectador.com/opinion/columnistas/oscar-sevillano/francia-marquez-dapa-y-el-helicoptero/"
    },
    {
        "article-type": "column",
        "author": "Madame Papita",
        "date": "2023-03-03",
        "publication": "el-espectador",
        "title": "Salve usted la patria",
        "url": "https://www.elespectador.com/opinion/columnistas/madame-papita/salve-usted-la-patria/"
    },
    {
        "article-type": "column",
        "author": "Hern\u00e1n Gonz\u00e1lez Rodr\u00edguez",
        "date": "2023-03-03",
        "publication": "el-espectador",
        "title": "Econom\u00eda 2022 y proyecciones 2023",
        "url": "https://www.elespectador.com/opinion/columnistas/hernan-gonzalez-rodriguez/economia-2022-y-proyecciones-2023/"
    },
    {
        "article-type": "column",
        "author": "Ricardo Bada",
        "date": "2023-03-03",
        "publication": "el-espectador",
        "title": "90 a\u00f1os del estreno de \u00c9xtasis",
        "url": "https://www.elespectador.com/opinion/columnistas/ricardo-bada/90-anos-del-estreno-de-extasis/"
    },
    {
        "article-type": "column",
        "author": "Juan Felipe Carrillo G\u00e1faro",
        "date": "2023-03-03",
        "publication": "el-espectador",
        "title": "F\u00fatbol salvaje",
        "url": "https://www.elespectador.com/opinion/columnistas/juan-felipe-carrillo-gafaro/futbol-salvaje/"
    },
    {
        "article-type": "column",
        "author": "Pablo Parra Gallego*",
        "date": "2023-03-03",
        "publication": "el-espectador",
        "title": "El desminado humanitario en Colombia es una buena inversi\u00f3n",
        "url": "https://www.elespectador.com/colombia-20/analistas/el-desminado-humanitario-en-colombia-es-una-buena-inversion/"
    },
    {
        "article-type": "column",
        "author": "Las Igualadas",
        "date": "2023-03-03",
        "publication": "el-espectador",
        "title": "La menopausia y la falsa idea de que estamos enfermas y somos desechables",
        "url": "https://www.elespectador.com/opinion/columnistas/las-igualadas/la-menopausia-y-la-falsa-idea-de-que-estamos-enfermas-y-somos-desechables/"
    },
    {
        "article-type": "column",
        "author": "Jos\u00e9 Fernando Isaza",
        "date": "2023-03-02",
        "publication": "el-espectador",
        "title": "Peor",
        "url": "https://www.elespectador.com/opinion/columnistas/jose-fernando-isaza/peor/"
    },
    {
        "article-type": "column",
        "author": "Cristina Nicholls Ocampo",
        "date": "2023-03-02",
        "publication": "el-espectador",
        "title": "Drogas: el debate que nos deben",
        "url": "https://www.elespectador.com/opinion/columnistas/cristina-nicholls/drogas-el-debate-que-nos-deben/"
    },
    {
        "article-type": "editorial",
        "author": null,
        "date": "2023-03-03",
        "publication": "el-tiempo",
        "title": "Los cultivos il\u00edcitos",
        "url": "https://www.eltiempo.com/opinion/editorial/los-cultivos-ilicitos-editorial-el-tiempo-746799"
    },
    {
        "article-type": "column",
        "author": "Mois\u00e9s Wasserman",
        "date": "2023-03-03",
        "publication": "el-tiempo",
        "title": "Dahl y los neopuritanos",
        "url": "https://www.eltiempo.com/opinion/columnistas/moises-wasserman/dahl-y-los-neopuritanos-columna-de-moises-wasserman-746710"
    },
    {
        "article-type": "column",
        "author": "Ricardo Silva Romero",
        "date": "2023-03-03",
        "publication": "el-tiempo",
        "title": "Gestos",
        "url": "https://www.eltiempo.com/opinion/columnistas/ricardo-silva-romero/gestos-columna-de-ricardo-silva-romero-746745"
    },
    {
        "article-type": "column",
        "author": "Martha Ortiz",
        "date": "2023-03-03",
        "publication": "el-tiempo",
        "title": "Viva, tormenta de alto riesgo (I)",
        "url": "https://www.eltiempo.com/opinion/columnistas/martha-ortiz/viva-tormenta-de-alto-riesgo-i-columna-de-martha-ortiz-746762"
    },
    {
        "article-type": "column",
        "author": "Claudia Hakim",
        "date": "2023-03-03",
        "publication": "el-tiempo",
        "title": "\u00bfSomos reemplazables?",
        "url": "https://www.eltiempo.com/opinion/columnistas/claudia-hakim/somos-reemplazables-columna-de-claudia-hakim-746726"
    },
    {
        "article-type": "column",
        "author": "Eduardo Posada Carb\u00f3",
        "date": "2023-03-03",
        "publication": "el-tiempo",
        "title": "En tiempos de crisis",
        "url": "https://www.eltiempo.com/opinion/columnistas/eduardo-posada-carbo/en-tiempos-de-crisis-columna-de-eduardo-posada-carbo-746713"
    },
    {
        "article-type": "column",
        "author": "Alejandro Cheyne",
        "date": "2023-03-03",
        "publication": "el-tiempo",
        "title": "Serenidad en el Congreso",
        "url": "https://www.eltiempo.com/opinion/columnistas/alejandro-cheyne/serenidad-en-el-congreso-columna-de-alejandro-cheyne-746773"
    },
    {
        "article-type": "column",
        "author": "Martha Senn",
        "date": "2023-03-03",
        "publication": "el-tiempo",
        "title": "Excelente y accidentada \u2018Tosca\u2019, de Puccini",
        "url": "https://www.eltiempo.com/opinion/columnistas/martha-senn/excelente-y-accidentada-tosca-de-puccini-columna-de-martha-senn-746770"
    },
    {
        "article-type": "column",
        "author": "Alfredo Rangel",
        "date": "2023-03-03",
        "publication": "el-tiempo",
        "title": "Sometimiento, con glifosato",
        "url": "https://www.eltiempo.com/opinion/columnistas/alfredo-rangel/sometimiento-con-glifosato-columna-de-alfredo-rangel-746749"
    },
    {
        "article-type": "column",
        "author": "Salvo Basile",
        "date": "2023-03-03",
        "publication": "el-tiempo",
        "title": "Adaptarse al cambio",
        "url": "https://www.eltiempo.com/opinion/columnistas/salvo-basile/adaptarse-al-cambio-columna-de-salvo-basile-746741"
    }
]
