[
    {
        "article-type": "editorial",
        "author": null,
        "date": "2023-07-03",
        "publication": "el-colombiano",
        "title": "Radiograf\u00eda al listado de las grandes empresas ",
        "url": "https://www.elcolombiano.com/opinion/editoriales/radiografia-al-listado-de-las-grandes-empresas-NM21879073"
    },
    {
        "article-type": "editorial",
        "author": null,
        "date": "2023-07-03",
        "publication": "el-espectador",
        "title": "Mentiras en el caso de \u00d3scar Iv\u00e1n Zuluaga",
        "url": "https://www.elespectador.com/opinion/editorial/mentiras-en-el-caso-de-oscar-ivan-zuluaga/"
    },
    {
        "article-type": "column",
        "author": "Mar\u00eda Alejandra Medina Cartagena, Gazapera",
        "date": "2023-07-03",
        "publication": "el-espectador",
        "title": "Las diferencias entre \u00abhace\u00bb y \u00abdesde hace\u00bb",
        "url": "https://www.elespectador.com/opinion/columnistas/maria-alejandra-medina-cartagena-gazapera/las-diferencias-entre-hace-y-desde-hace/"
    },
    {
        "article-type": "column",
        "author": "Mar\u00eda Teresa Ronderos",
        "date": "2023-07-03",
        "publication": "el-espectador",
        "title": "Dabeiba, bandera y patria",
        "url": "https://www.elespectador.com/opinion/columnistas/maria-teresa-ronderos/dabeiba-bandera-y-patria/"
    },
    {
        "article-type": "column",
        "author": "Salom\u00f3n Kalmanovitz",
        "date": "2023-07-03",
        "publication": "el-espectador",
        "title": "La riqueza de El Cerrej\u00f3n",
        "url": "https://www.elespectador.com/opinion/columnistas/salomon-kalmanovitz/la-riqueza-de-el-cerrejon/"
    },
    {
        "article-type": "column",
        "author": "Leopoldo Villar Borda",
        "date": "2023-07-03",
        "publication": "el-espectador",
        "title": "\u00bfDe la c\u00e1rcel a la Casa Blanca?",
        "url": "https://www.elespectador.com/opinion/columnistas/leopoldo-villar-borda/de-la-carcel-a-la-casa-blanca/"
    },
    {
        "article-type": "column",
        "author": "Lorenzo Madrigal",
        "date": "2023-07-03",
        "publication": "el-espectador",
        "title": "Tribuno del pueblo",
        "url": "https://www.elespectador.com/opinion/columnistas/lorenzo-madrigal/tribuno-del-pueblo/"
    },
    {
        "article-type": "column",
        "author": "Sergio Ocampo Madrid",
        "date": "2023-07-03",
        "publication": "el-espectador",
        "title": "IA, \u00bfy escribir para qu\u00e9?",
        "url": "https://www.elespectador.com/opinion/columnistas/sergio-ocampo-madrid/ia-y-escribir-para-que/"
    },
    {
        "article-type": "column",
        "author": "Luis Carvajal Basto",
        "date": "2023-07-03",
        "publication": "el-espectador",
        "title": "Golpes no tan blandos contra los partidos",
        "url": "https://www.elespectador.com/opinion/columnistas/luis-carvajal-basto/golpes-no-tan-blandos-contra-los-partidos/"
    },
    {
        "article-type": "column",
        "author": "Daniel Mera Villamizar",
        "date": "2023-07-03",
        "publication": "el-espectador",
        "title": "Coalici\u00f3n pol\u00edtica de largo plazo para la reforma educativa",
        "url": "https://www.elespectador.com/opinion/columnistas/daniel-mera-villamizar/coalicion-politica-de-largo-plazo-para-la-reforma-educativa/"
    },
    {
        "article-type": "column",
        "author": "Indalecio Dangond B.",
        "date": "2023-07-03",
        "publication": "el-espectador",
        "title": "El deterioro de la Regi\u00f3n Caribe",
        "url": "https://www.elespectador.com/opinion/columnistas/indalecio-dangond-b-/el-deterioro-de-la-region-caribe/"
    },
    {
        "article-type": "column",
        "author": "El Espectador",
        "date": "2023-07-03",
        "publication": "el-espectador",
        "title": "Editorial en video: \u201cHay que proteger el proceso electoral\u201d",
        "url": "https://www.elespectador.com/opinion/columnistas/el-espectador/editorial-en-video-hay-que-proteger-el-proceso-electoral/"
    },
    {
        "article-type": "column",
        "author": "Marc Hofstetter",
        "date": "2023-07-02",
        "publication": "el-espectador",
        "title": "De cada 100 ",
        "url": "https://www.elespectador.com/opinion/columnistas/marc-hofstetter/de-cada-100/"
    },
    {
        "article-type": "column",
        "author": "H\u00e9ctor Abad Faciolince",
        "date": "2023-07-02",
        "publication": "el-espectador",
        "title": "Una victoria para Victoria",
        "url": "https://www.elespectador.com/opinion/columnistas/hector-abad-faciolince/una-victoria-para-victoria/"
    },
    {
        "article-type": "column",
        "author": "La Candidata",
        "date": "2023-07-02",
        "publication": "el-espectador",
        "title": "Cap\u00edtulo 39: Vicky D\u00e1vila y 93 horas de silencio",
        "url": "https://www.elespectador.com/opinion/columnistas/la-candidata/gustavo-petro-amenaza-a-los-gilinski-y-vicky-davila-desaparece-por-cuatro-dias/"
    },
    {
        "article-type": "column",
        "author": "Jaime Bayly",
        "date": "2023-07-02",
        "publication": "el-espectador",
        "title": "Mi imperio est\u00e1 en ruinas",
        "url": "https://www.elespectador.com/opinion/columnistas/jbayly/mi-imperio-esta-en-ruinas/"
    },
    {
        "article-type": "column",
        "author": "Armando Montenegro",
        "date": "2023-07-02",
        "publication": "el-espectador",
        "title": "Hacia el colapso de la salud",
        "url": "https://www.elespectador.com/opinion/columnistas/armando-montenegro/hacia-el-colapso-de-la-salud/"
    },
    {
        "article-type": "column",
        "author": "Rodrigo Uprimny",
        "date": "2023-07-02",
        "publication": "el-espectador",
        "title": "Los olvidados",
        "url": "https://www.elespectador.com/opinion/columnistas/rodrigo-uprimny/los-olvidados/"
    },
    {
        "article-type": "editorial",
        "author": null,
        "date": "2023-07-03",
        "publication": "el-tiempo",
        "title": "Partidos aut\u00f3nomos",
        "url": "https://www.eltiempo.com/opinion/editorial/editorial-de-el-tiempo-del-3-de-julio-de-2023-partidos-autonomos-782821"
    },
    {
        "article-type": "column",
        "author": "Juan Lozano",
        "date": "2023-07-03",
        "publication": "el-tiempo",
        "title": "El nido de la corrupci\u00f3n",
        "url": "https://www.eltiempo.com/opinion/columnistas/juan-lozano/columna-de-juan-lozano-el-nido-de-la-corrupcion-782804"
    },
    {
        "article-type": "column",
        "author": "Nancy Patricia Guti\u00e9rrez",
        "date": "2023-07-03",
        "publication": "el-tiempo",
        "title": "Hambre en La Guajira y transici\u00f3n energ\u00e9tica",
        "url": "https://www.eltiempo.com/opinion/columnistas/nancy-patricia-gutierrez/columna-de-nancy-patricia-gutierrez-hambre-en-la-guajira-y-transicion-energetica-782805"
    },
    {
        "article-type": "column",
        "author": "Luis Felipe Henao",
        "date": "2023-07-03",
        "publication": "el-tiempo",
        "title": "Gracias, JEP, por revelar la verdad",
        "url": "https://www.eltiempo.com/opinion/columnistas/luis-felipe-henao/columna-de-luis-felipe-henao-gracias-jep-por-revelar-la-verdad-782813"
    },
    {
        "article-type": "column",
        "author": "Diego Santos",
        "date": "2023-07-03",
        "publication": "el-tiempo",
        "title": "Telegram se consolida como la plataforma m\u00e1s potente del mundo",
        "url": "https://www.eltiempo.com/opinion/columnistas/diego-santos/columna-de-diego-santos-telegram-la-plataforma-mas-potente-del-mundo-782803"
    },
    {
        "article-type": "column",
        "author": "David Racero",
        "date": "2023-07-03",
        "publication": "el-tiempo",
        "title": "Congreso del cambio",
        "url": "https://www.eltiempo.com/opinion/columnistas/david-racero/columna-de-david-racero-congreso-del-cambio-782815"
    },
    {
        "article-type": "column",
        "author": "Paola Ochoa",
        "date": "2023-07-03",
        "publication": "el-tiempo",
        "title": "Autodesprecio",
        "url": "https://www.eltiempo.com/opinion/columnistas/paola-ochoa/columna-de-paola-ochoa-autodesprecio-782814"
    },
    {
        "article-type": "column",
        "author": "Guillermo Santos Calder\u00f3n",
        "date": "2023-07-03",
        "publication": "el-tiempo",
        "title": "Alcaldes, sean digitales",
        "url": "https://www.eltiempo.com/opinion/columnistas/guillermo-santos-calderon/columna-de-guillermo-santos-calderon-alcaldes-sean-digitales-782819"
    },
    {
        "article-type": "column",
        "author": "Melba Escobar",
        "date": "2023-07-03",
        "publication": "el-tiempo",
        "title": "El precio de estar vivo",
        "url": "https://www.eltiempo.com/opinion/columnistas/melba-escobar/columna-de-melba-escobar-el-precio-de-estar-vivo-782809"
    }
]
