[
    {
        "article-type": "editorial",
        "author": null,
        "date": "2023-08-14",
        "publication": "el-colombiano",
        "title": "Se desinfla el globo chino",
        "url": "https://www.elcolombiano.com/opinion/columnistas/se-desinfla-el-globo-chino-LC22134852"
    },
    {
        "article-type": "editorial",
        "author": null,
        "date": "2023-08-14",
        "publication": "el-espectador",
        "title": "S\u00ed, Colombia puede ser potencia mundial de f\u00fatbol",
        "url": "https://www.elespectador.com/opinion/editorial/si-colombia-puede-ser-potencia-mundial-de-futbol/"
    },
    {
        "article-type": "column",
        "author": "Juan Carlos G\u00f3mez",
        "date": "2023-08-14",
        "publication": "el-espectador",
        "title": "\u00bfSe salvar\u00e1 Wikipedia?",
        "url": "https://www.elespectador.com/opinion/columnistas/juan-carlos-gomez/se-salvara-wikipedia/"
    },
    {
        "article-type": "column",
        "author": "Jorge Tovar",
        "date": "2023-08-14",
        "publication": "el-espectador",
        "title": "Columna de Jorge Tovar: Mujeres vs. hombres",
        "url": "https://www.elespectador.com/opinion/columnistas/jorge-tovar/mujeres-vs-hombres/"
    },
    {
        "article-type": "column",
        "author": "Antonio Casale",
        "date": "2023-08-14",
        "publication": "el-espectador",
        "title": "Columna de Antonio Casale: Lo que viene",
        "url": "https://www.elespectador.com/opinion/columnistas/antonio-casale/lo-que-viene/"
    },
    {
        "article-type": "column",
        "author": "Mar\u00eda Alejandra Medina Cartagena, Gazapera",
        "date": "2023-08-14",
        "publication": "el-espectador",
        "title": "\u00bfSe dice \u00abveinti\u00fan p\u00e1ginas\u00bb o \u00abveintiuna p\u00e1ginas\u00bb?",
        "url": "https://www.elespectador.com/opinion/columnistas/maria-alejandra-medina-cartagena-gazapera/se-dice-veintiun-paginas-o-veintiuna-paginas/"
    },
    {
        "article-type": "column",
        "author": "Salom\u00f3n Kalmanovitz",
        "date": "2023-08-14",
        "publication": "el-espectador",
        "title": "La macroeconom\u00eda de Petro",
        "url": "https://www.elespectador.com/opinion/columnistas/salomon-kalmanovitz/la-macroeconomia-de-petro/"
    },
    {
        "article-type": "column",
        "author": "Lorenzo Madrigal",
        "date": "2023-08-14",
        "publication": "el-espectador",
        "title": "La verdad no es hoy",
        "url": "https://www.elespectador.com/opinion/columnistas/lorenzo-madrigal/la-verdad-no-es-hoy/"
    },
    {
        "article-type": "column",
        "author": "Mar\u00eda Alejandra Villamizar",
        "date": "2023-08-14",
        "publication": "el-espectador",
        "title": "De h\u00e9roes y m\u00e1rtires",
        "url": "https://www.elespectador.com/opinion/columnistas/maria-alejandra-villamizar/de-heroes-y-martires/"
    },
    {
        "article-type": "column",
        "author": "Mar\u00eda Teresa Ronderos",
        "date": "2023-08-14",
        "publication": "el-espectador",
        "title": "La patota digital y las mentiras \u201c\u00e0 la Char\u201d",
        "url": "https://www.elespectador.com/opinion/columnistas/maria-teresa-ronderos/la-patota-digital-y-las-mentiras-a-la-char/"
    },
    {
        "article-type": "column",
        "author": "Luis Carvajal Basto",
        "date": "2023-08-14",
        "publication": "el-espectador",
        "title": "\u00bfEs factible un acuerdo?",
        "url": "https://www.elespectador.com/opinion/columnistas/luis-carvajal-basto/es-factible-un-acuerdo/"
    },
    {
        "article-type": "column",
        "author": "Fernando Barbosa",
        "date": "2023-08-14",
        "publication": "el-espectador",
        "title": "\u00bfNuevo capitalismo japon\u00e9s?",
        "url": "https://www.elespectador.com/opinion/columnistas/fernando-barbosa/nuevo-capitalismo-japones/"
    },
    {
        "article-type": "column",
        "author": "El Espectador",
        "date": "2023-08-14",
        "publication": "el-espectador",
        "title": "Editorial en video: \u201cNecesitamos total claridad sobre el supuesto plan del ELN\u201d",
        "url": "https://www.elespectador.com/opinion/columnistas/el-espectador/editorial-en-video-necesitamos-total-claridad-sobre-el-supuesto-plan-del-eln/"
    },
    {
        "article-type": "column",
        "author": "Gilles Bertrand*",
        "date": "2023-08-14",
        "publication": "el-espectador",
        "title": "Juventudes de Colombia: la generaci\u00f3n de la no repetici\u00f3n",
        "url": "https://www.elespectador.com/colombia-20/analistas/juventudes-de-colombia-la-generacion-de-la-no-repeticion/"
    },
    {
        "article-type": "column",
        "author": "Eduardo Sarmiento",
        "date": "2023-08-13",
        "publication": "el-espectador",
        "title": "Se agrava el estancamiento",
        "url": "https://www.elespectador.com/opinion/columnistas/eduardo-sarmiento/se-agrava-el-estancamiento/"
    },
    {
        "article-type": "column",
        "author": "Jaime Bayly",
        "date": "2023-08-13",
        "publication": "el-espectador",
        "title": "Un hombre es un archipi\u00e9lago",
        "url": "https://www.elespectador.com/opinion/columnistas/jbayly/un-hombre-es-un-archipielago/"
    },
    {
        "article-type": "column",
        "author": "Paul Krugman",
        "date": "2023-08-13",
        "publication": "el-espectador",
        "title": "El clima ahora es una cuesti\u00f3n de guerra cultural",
        "url": "https://www.elespectador.com/opinion/columnistas/paul-krugman/el-clima-ahora-es-una-cuestion-de-guerra-cultural/"
    },
    {
        "article-type": "column",
        "author": "Rodrigo Uprimny",
        "date": "2023-08-13",
        "publication": "el-espectador",
        "title": "Clement Attlee: un reformador eficaz",
        "url": "https://www.elespectador.com/opinion/columnistas/rodrigo-uprimny/clement-attlee-un-reformador-eficaz/"
    },
    {
        "article-type": "editorial",
        "author": null,
        "date": "2023-08-14",
        "publication": "el-tiempo",
        "title": "Urgen compromisos",
        "url": "https://www.eltiempo.com/opinion/editorial/editorial-de-el-tiempo-del-14-de-agosto-de-2023-urgen-compromisos-795798"
    },
    {
        "article-type": "column",
        "author": "Juan Lozano",
        "date": "2023-08-14",
        "publication": "el-tiempo",
        "title": "Ant\u00eddoto contra el pesimismo",
        "url": "https://www.eltiempo.com/opinion/columnistas/juan-lozano/columna-de-juan-lozano-antidoto-contra-el-pesimismo-795815"
    },
    {
        "article-type": "column",
        "author": "Luis Felipe Henao",
        "date": "2023-08-14",
        "publication": "el-tiempo",
        "title": "\u2018Potencia mundial de las drogas y el delito\u2019",
        "url": "https://www.eltiempo.com/opinion/columnistas/luis-felipe-henao/columna-de-luis-felipe-henao-potencia-mundial-de-las-drogas-y-el-delito-795808"
    },
    {
        "article-type": "column",
        "author": "Mariana Ardila Trujillo",
        "date": "2023-08-14",
        "publication": "el-tiempo",
        "title": "Un giro en la conversaci\u00f3n",
        "url": "https://www.eltiempo.com/opinion/columnistas/otros-columnistas/columna-de-mariana-ardila-trujillo-un-giro-en-la-conversacion-795816"
    },
    {
        "article-type": "column",
        "author": "Diego Santos",
        "date": "2023-08-14",
        "publication": "el-tiempo",
        "title": "YouTube Shorts tambi\u00e9n es una adicci\u00f3n para los ni\u00f1os",
        "url": "https://www.eltiempo.com/opinion/columnistas/diego-santos/columna-de-diego-santos-youtube-shorts-tambien-es-una-adiccion-para-los-ninos-795824"
    },
    {
        "article-type": "column",
        "author": "Paola Ochoa",
        "date": "2023-08-14",
        "publication": "el-tiempo",
        "title": "El se\u00f1or Roa",
        "url": "https://www.eltiempo.com/opinion/columnistas/paola-ochoa/columna-de-paola-ochoa-el-senor-roa-795820"
    },
    {
        "article-type": "column",
        "author": "\u00d3scar Dom\u00ednguez Giraldo",
        "date": "2023-08-14",
        "publication": "el-tiempo",
        "title": "Se\u00f1ora de 485 abriles",
        "url": "https://www.eltiempo.com/opinion/columnistas/oscar-dominguez-giraldo/columna-de-oscar-dominguez-senora-de-485-abriles-795807"
    },
    {
        "article-type": "column",
        "author": "Melba Escobar",
        "date": "2023-08-14",
        "publication": "el-tiempo",
        "title": "S\u00e1calo t\u00fa",
        "url": "https://www.eltiempo.com/opinion/columnistas/melba-escobar/columna-de-melba-escobar-sacalo-tu-795821"
    },
    {
        "article-type": "column",
        "author": "Jorge Barraza",
        "date": "2023-08-14",
        "publication": "el-tiempo",
        "title": "La Libertadores vuelve a encantar",
        "url": "https://www.eltiempo.com/opinion/columnistas/jorge-barraza/columna-de-jorge-barraza-la-libertadores-vuelve-a-encantar-795826"
    }
]
